__init__.py
hi.py
materialized-0.0.0.dist-info/METADATA
materialized-0.0.0.dist-info/WHEEL
materialized-0.0.0.dist-info/top_level.txt
materialized-0.0.0.dist-info/RECORD
