Metadata-Version: 2.1
Name: materialized
Version: 0.0.0
Summary: Materialized Intelligence SDK (Alias)
Author-email: Seth Kimmel <seth.kimmel3@gmail.com>
Project-URL: Homepage, https://materialized.dev
